devjoni/stllib/devj-musa-LB1-nothreads.stl
devjoni/stllib/devj-musa-LB2-nothreads.stl
devjoni/stllib/devj-musa-baseplate-nothreads.stl
devjoni/stllib/devj-musa-rail-counter-nothreads.stl
devjoni/stllib/devj-musa-rail.stl
devjoni/stllib/devj-palloframe-L10-basepiece-square.stl
devjoni/stllib/devj-palloframe-L10-basepiece-triangle.stl
devjoni/stllib/devj-palloframe-L20-basepiece-square.stl
devjoni/stllib/devj-palloframe-L20-basepiece-triangle.stl
devjoni/stllib/devj-palloframe-L5-basepiece-square.stl
devjoni/stllib/devj-palloframe-L5-basepiece-triangle.stl
devjoni/stllib/devj-papalink-femcon-bottom.stl
devjoni/stllib/devj-papalink-femcon-top.stl
devjoni/stllib/devj-papalink-malecon-bottom.stl
devjoni/stllib/devj-papalink-malecon-mid.stl
devjoni/stllib/devj-papalink-malecon-top-withprotector.stl
devjoni/stllib/devj-r30-emitter-base.stl
devjoni/stllib/devj-r30-emitter-lid.stl
devjoni/stllib/devj-r30-emitter-spacer.stl
devjoni/stllib/devj-r30-socket-base.stl
devjoni/stllib/devj-r30-socket-minus.stl
devjoni/stllib/devj-r30-socket-plus.stl
devjoni/stllib/devj-simpleled-mini.stl
devjoni/stllib/devj-simpleled-profile.stl
devjoni/stllib/stllib.py
devjoni_stllib-0.0.2.dist-info/LICENSE
devjoni_stllib-0.0.2.dist-info/METADATA
devjoni_stllib-0.0.2.dist-info/WHEEL
devjoni_stllib-0.0.2.dist-info/top_level.txt
devjoni_stllib-0.0.2.dist-info/RECORD
