Metadata-Version: 2.2
Name: devjoni-stllib
Version: 0.0.2
Summary: All released 3D models by DEV Joni
Author-email: DEV Joni <solutions@devjoni.com>
Project-URL: Homepage, https://github.com/devjonix/stllib
Project-URL: Bug Tracker, https://github.com/devjonix/stllib/issues
Keywords: devjoni,3d-models
Classifier: Programming Language :: Python :: 3
Classifier: License :: OSI Approved :: GNU General Public License v3 (GPLv3)
Classifier: Operating System :: OS Independent
Classifier: Topic :: Multimedia :: Graphics :: 3D Modeling
Classifier: Intended Audience :: Science/Research
Requires-Python: >=3.8
License-File: LICENSE
